{
    "verbose": true,
    "socket_port":5000,
    "websocket_port":5001,
    "websocket_accepted_origins":[
        "https://localhost:3000",
        "http://localhost:3000",
        ""
    ],
    "disable_modbus":false,
    "modbus_host":"127.0.0.1",
    "modbus_port":502,
    "modbus_slave_num":1,
    "modbus_timeout":1.0,
    "modbus_sleep_inteval":0.125,
    "cert_file":"cert/cert.pem",
    "key_file":"cert/key.pem",
    "client_ca_file":"cert/cacert.pem",
    "debug": false,
    "pin_assignments": {
        "F1": 8452,
        "F2": 8453,
        "F3": 8454,
        "F4": 8455,
        "F5": 0,
        "STEP": 8417,
        "MENU": 8422,
        "SELECT": 8423,
        "EDIT": 8448,
        "DATA": 8449,
        "FCTN": 8450,
        "SHIFT": 16384,
        "PREV": 8451,
        "<": 8418,
        "^": 8420,
        "v": 8419,
        ">": 8421,
        "NEXT": 0,
        "ITEM": 8357,
        "BKSPC": 8387,
        "RESET": 8416,
        "9": 8356,
        "8": 8386,
        "7": 8391,
        "6": 8355,
        "5": 8385,
        "4": 8390,
        "3": 8354,
        "2": 8384,
        "1": 8389,
        ",": 8353,
        ".": 8359,
        "0": 8388,
        "I/O": 8352,
        "POSN": 8358,
        "-": 8353,
        "ENTER": 8327,
        "TOOL1": 8326,
        "TOOL2": 8325,
        "MVMU": 8324,
        "SETUP": 8323,
        "STATUS": 8322,
        "+X": 8261,
        "-X": 8291,
        "HOLD": 8321,
        "+Y": 8260,
        "-Y": 8290,
        "FWD": 8320,
        "+Z": 8259,
        "-Z": 8289,
        "BWD": 8295,
        "+XR": 8258,
        "-XR": 8288,
        "COORD": 8294,
        "+YR": 8257,
        "-YR": 8263,
        "+%": 8293,
        "+ZR": 8256,
        "-ZR": 8262,
        "-%": 8292
    },
    "log_level": "info",
    "multiprocess_logging": true,
    "multiprocess_logging_port": 10000 
}
